cosmopawn/__init__.py
cosmopawn/cosmopawn.py
cosmopawn-1.1.0.dist-info/LICENSE
cosmopawn-1.1.0.dist-info/METADATA
cosmopawn-1.1.0.dist-info/WHEEL
cosmopawn-1.1.0.dist-info/top_level.txt
cosmopawn-1.1.0.dist-info/RECORD
