Metadata-Version: 2.1
Name: cosmopawn
Version: 1.1.0
Summary: An API wrapper for the CosmoPawn API in Python
Author: pennacap
Project-URL: Homepage, https://github.com/pennacap/cosmopawn-py
Project-URL: Bug Tracker, https://github.com/pennacap/cosmopawn-py/issues
Classifier: Programming Language :: Python :: 3
Classifier: License :: OSI Approved :: MIT License
Classifier: Operating System :: OS Independent
Requires-Python: >=3.6
License-File: LICENSE
